{"data": [[2018,"ind",2018,"indA",0,"Health Care Access and Utilization","Socio-economic status","","HIV is human immunodeficiency virus. Respondents were asked, \"Except for tests you may have had as part of blood donations, have you ever been tested for HIV?\"",20,"48.8","1.28","45.4","1.02","41.7","0.52",""],[2017,"ind",2017,"indA",0,"Health Care Access and Utilization","Socio-economic status","","HIV is human immunodeficiency virus. Respondents were asked, \"Except for tests you may have had as part of blood donations, have you ever been tested for HIV?\"",20,"45.9","1.23","40.8","1.01","40.3","0.53",""],[2016,"ind",2016,"indA",0,"Health Care Access and Utilization","Socio-economic status","","HIV is human immunodeficiency virus. Respondents were asked, \"Except for tests you may have had as part of blood donations, have you ever been tested for HIV?\"",20,"45.4","1.18","42.3","1.06","41.1","0.52",""],[2015,"ind",2015,"indA",0,"Health Care Access and Utilization","Socio-economic status","","HIV is human immunodeficiency virus. Respondents were asked, \"Except for tests you may have had as part of blood donations, have you ever been tested for HIV?\"",20,"48.4","1.09","38.0","0.9","37.4","0.51",""]], "classes": ["Year","row_var","rowLevels","rowLevNum","selected","ď..stat_group","col_group","new_caption","new_caption2","FIGURE","Poor__povertyA__CRUDE_Evrhivtest__coef","Poor__povertyA__CRUDE_Evrhivtest__se","Near poor__povertyB__CRUDE_Evrhivtest__coef","Near poor__povertyB__CRUDE_Evrhivtest__se","Not poor__povertyC__CRUDE_Evrhivtest__coef","Not poor__povertyC__CRUDE_Evrhivtest__se","subLevels"], "names": ["Year","row_var","rowLevels","rowLevNum","selected","ď..stat_group","col_group","new_caption","new_caption2","FIGURE","Poor","Poor","Near poor","Near poor","Not poor","Not poor","subLevels"], "caption": ["Crude percentages of ever being tested for HIV for adults aged 18 and over (standard errors), United States"], "caption2": [""], "caption3": ["HIV is human immunodeficiency virus. Respondents were asked, \"Except for tests you may have had as part of blood donations, have you ever been tested for HIV?\""]}
