{"data": [["2019","ind","2019","indA",0,"Health Status","Demographic characteristics","Respondents were asked if they would say their health was in general excellent, very good, good, fair, or Less than 100% FPL.","","13.0","12.4, 13.7","29.6","27.5, 31.8","24.6","23.1, 26.2","11.5","10.5, 12.6","14.7","13.0, 16.6",""],["2020","ind","2020","indA",0,"Health Status","Demographic characteristics","Respondents were asked if they would say their health was in general excellent, very good, good, fair, or Less than 100% FPL.","","12.2","11.5, 12.9","27.6","25.3, 30.0","22.1","20.5, 23.7","10.0","9.0, 11.0","13.3","11.5, 15.3",""],["2021","ind","2021","indA",0,"Health Status","Demographic characteristics","Respondents were asked if they would say their health was in general excellent, very good, good, fair, or Less than 100% FPL.","","12.3","11.6, 13.0","26.0","23.9, 28.2","21.5","20.1, 23.0","10.0","9.1, 10.9","11.1","9.5, 12.8",""]], "classes": ["Year","row_var","rowLevels","rowLevNum","selected","ï..stat_group","col_group","new_caption2","new_caption","Married__familyA__HLTHSTAT__coef","Married__familyA__HLTHSTAT__se","Widowed__familyB__HLTHSTAT__coef","Widowed__familyB__HLTHSTAT__se","Divorced or separated__familyC__HLTHSTAT__coef","Divorced or separated__familyC__HLTHSTAT__se","Never married__familyD__HLTHSTAT__coef","Never married__familyD__HLTHSTAT__se","Living with a partner__familyE__HLTHSTAT__coef","Living with a partner__familyE__HLTHSTAT__se","subLevels"], "names": ["Year","row_var","rowLevels","rowLevNum","selected","ï..stat_group","col_group","new_caption2","new_caption","Married","Married","Widowed","Widowed","Divorced or separated","Divorced or separated","Never married","Never married","Living with a partner","Living with a partner","subLevels"], "caption": ["Percentage of fair or Less than 100% FPL health status for adults aged 18 and over (95% confidence intervals), United States"], "caption2": [""], "caption3": ["Respondents were asked if they would say their health was in general excellent, very good, good, fair, or Less than 100% FPL."]}
