{"data": [["2019","ind","2019","indA",0,"Health Care Access and Utilization","Demographic characteristics","Respondents were asked if they took prescription medication at any time in the past 12 months.","","69.3","68.5, 70.0","53.7","51.9, 55.4",""],["2020","ind","2020","indA",0,"Health Care Access and Utilization","Demographic characteristics","Respondents were asked if they took prescription medication at any time in the past 12 months.","","68.2","67.4, 69.1","52.4","50.6, 54.3",""]], "classes": ["Year","row_var","rowLevels","rowLevNum","selected","ï..stat_group","col_group","new_caption2","new_caption","U.S.-born__nativityA__PRESCMED__coef","U.S.-born__nativityA__PRESCMED__se","Foreign-born__nativityB__PRESCMED__coef","Foreign-born__nativityB__PRESCMED__se","subLevels"], "names": ["Year","row_var","rowLevels","rowLevNum","selected","ï..stat_group","col_group","new_caption2","new_caption","U.S.-born","U.S.-born","Foreign-born","Foreign-born","subLevels"], "caption": ["Percentage of prescription medication use in the past 12 months for adults aged 18 and over (95% confidence intervals), United States"], "caption2": [""], "caption3": ["Respondents were asked if they took prescription medication at any time in the past 12 months."]}
